numerical_distributions/Binomialdistribution.py
numerical_distributions/Gaussiandistribution.py
numerical_distributions/Generaldistribution.py
numerical_distributions/__init__.py
numerical_distributions-0.1.dist-info/METADATA
numerical_distributions-0.1.dist-info/WHEEL
numerical_distributions-0.1.dist-info/top_level.txt
numerical_distributions-0.1.dist-info/RECORD
