Metadata-Version: 2.1
Name: numerical-distributions
Version: 0.1
Summary: Gaussian and Binomial distributions
Home-page: UNKNOWN
Author: Palak Gupta
Author-email: palakgupta889@gmail.com
License: UNKNOWN
Platform: UNKNOWN
